htcdaskgateway/__init__.py
htcdaskgateway/_version.py
htcdaskgateway/cluster.py
htcdaskgateway/gateway.py
htcdaskgateway/setup_condor.py
ncsa_htcdaskgateway-1.0.4.dist-info/METADATA
ncsa_htcdaskgateway-1.0.4.dist-info/WHEEL
ncsa_htcdaskgateway-1.0.4.dist-info/entry_points.txt
ncsa_htcdaskgateway-1.0.4.dist-info/RECORD
