Metadata-Version: 2.4
Name: ncsa-htcdaskgateway
Version: 1.0.4
Summary: Launches a Dask Gateway cluster in K8s and joins HTCondor workers to it
Project-URL: Homepage, https://github.com/ncsa/dagster-ncsa
Project-URL: Bug Tracker, https://github.com/ncsa/dagster-ncsa/issues
Project-URL: Discussions, https://github.com/ncsa/dagster-ncsa/discussions
Project-URL: Changelog, https://github.com/ncsa/dagster-ncsa/releases
Author-email: Ben Galewsky <bengal1@illinois.edu>, "Maria P. Acosta F./Fermilab EAF project" <macosta@fnal.gov>
Classifier: Development Status :: 1 - Planning
Classifier: Intended Audience :: Developers
Classifier: Intended Audience :: Science/Research
Classifier: License :: OSI Approved :: BSD License
Classifier: Operating System :: OS Independent
Classifier: Programming Language :: Python
Classifier: Programming Language :: Python :: 3
Classifier: Programming Language :: Python :: 3 :: Only
Classifier: Programming Language :: Python :: 3.9
Classifier: Programming Language :: Python :: 3.10
Classifier: Programming Language :: Python :: 3.11
Classifier: Programming Language :: Python :: 3.12
Classifier: Programming Language :: Python :: 3.13
Classifier: Topic :: Scientific/Engineering
Classifier: Typing :: Typed
Requires-Python: >=3.9
Requires-Dist: dask-gateway==2024.1.0
Requires-Dist: pexpect
Provides-Extra: dev
Requires-Dist: ruff; extra == 'dev'
